gundi_client/__init__.py
gundi_client/auth.py
gundi_client/client.py
gundi_client/settings.py
gundi_client-1.1.0.dist-info/LICENSE
gundi_client-1.1.0.dist-info/METADATA
gundi_client-1.1.0.dist-info/WHEEL
gundi_client-1.1.0.dist-info/RECORD
